ansible_jupyter_widgets/__init__.py
ansible_jupyter_widgets/widgets.py
ansible_jupyter_widgets-1.0.dist-info/LICENSE.md
ansible_jupyter_widgets-1.0.dist-info/METADATA
ansible_jupyter_widgets-1.0.dist-info/WHEEL
ansible_jupyter_widgets-1.0.dist-info/top_level.txt
ansible_jupyter_widgets-1.0.dist-info/RECORD
